<?xml version="1.0" encoding="UTF-8"?>

<root crawl_date="2015-04-09 15:10:12">
  <user_info user_id="5504780147" user_url="http://weibo.cn/u/5504780147?f=search_0">
    <weibo_count>20</weibo_count>
    <follow_count>0</follow_count>
    <fans_count>5</fans_count>
    <性别>男</性别>
    <生日>射手座</生日>
    <head_image>http://tp4.sinaimg.cn/5504780147/180/5718476864/1</head_image>
    <昵称>MaMOPple-sa</昵称>
    <地区>辽宁 营口</地区>
  </user_info>
  <weibo weibo_id="M_CcotLwi3y">
    <weibo_sender>MaMOPple-sa</weibo_sender>
    <weibo_content>:【贵阳市五金商场暗门 藏了黄碟窝点】6¤月25日,贵阳市云岩区多部门联合执法,查获老客车站五金商场内一非法光碟窝点:在不足50平米的仓库内,执法人员收缴千余张淫秽光碟及10万张盗版光盘。</weibo_content>
    <weibo_count like_count="0" forward_count="0" comment_count="0"/>
    <weibo_date>今天 02:17 </weibo_date>
    <weibo_from>来自微博 weibo.com</weibo_from>
  </weibo>
</root>
