<?xml version="1.0" encoding="UTF-8"?>

<root crawl_date="2015-04-09 15:08:41">
  <user_info user_id="3395174970" user_url="http://weibo.cn/u/3395174970?f=search_0">
    <weibo_count>54898</weibo_count>
    <follow_count>2007</follow_count>
    <fans_count>6638</fans_count>
    <性别>男</性别>
    <简介>国际品牌发明专利防水防烟救生呼吸器与氧空气压缩气瓶装置]专利号201110063592,8寻找投资者QQ号2871680108張勇。</简介>
    <生日>1957-02-19</生日>
    <认证>“一种无笔水墨画的制作方法”发明人</认证>
    <head_image>http://tp3.sinaimg.cn/3395174970/180/5718605736/1</head_image>
    <认证信息>“一种无笔水墨画的制作方法”发明人</认证信息>
    <昵称>世界发明張勇的无笔水墨画</昵称>
    <地区>山东 济南</地区>
  </user_info>
  <weibo weibo_id="M_CcqI75zwm">
    <weibo_sender>世界发明張勇的无笔水墨画</weibo_sender>
    <weibo_content>#新闻联播#国际品牌发明专利证书,防水防烟救生呼吸器与氧空气压缩气瓶装置。水陆多功能救命产品,能潜水,全球买断,—口价600万人民币,手机号13791117735張勇。 新闻联播 [位置]机床二厂路</weibo_content>
    <weibo_forward forward_reason="转发理由://@世界发明張勇的无笔水墨画:世界领先?//@世界发明張勇的无笔水墨画:使用于,矿井透水,幼儿园,院校,高楼,客车,司机,洪水,海上船只,公共场所等。  "> 转发了 世界发明張勇的无笔水墨画 的微博:</weibo_forward>
    <weibo_image>http://ww2.sinaimg.cn/bmiddle/ca5e423ajw1eiow45aps2j20a00dc0sr.jpg</weibo_image>
    <weibo_count like_count="0" forward_count="0" comment_count="0"/>
    <weibo_date>今天 07:58 </weibo_date>
    <weibo_from>来自新浪微博4G版</weibo_from>
  </weibo>
</root>
