<?xml version="1.0" encoding="UTF-8"?>

<root crawl_date="2015-04-09 14:49:55">
  <user_info user_id="5513372353" user_url="http://weibo.cn/u/5513372353?f=search_0">
    <weibo_count>32</weibo_count>
    <follow_count>47</follow_count>
    <fans_count>59</fans_count>
    <性别>女</性别>
    <head_image>http://tp2.sinaimg.cn/5513372353/180/5721861161/0</head_image>
    <昵称>King韩倌茗责</昵称>
    <地区>广东 深圳</地区>
  </user_info>
  <weibo weibo_id="M_Cctlxv736">
    <weibo_sender>King韩倌茗责</weibo_sender>
    <weibo_content>:【斯巴鲁将发力在华市场】2014年,中国再度成为全球第一大汽车销售市场,这一年也是斯巴鲁进入中国市场第十个年头,尽管在入华时间上还显得有些“年轻”,但以SUV车型为主的产品矩阵却是与中国市场近年的“SUV热”不谋而合,这也更加确定了斯巴鲁深耕中国市场的决心。</weibo_content>
    <weibo_image>http://ww2.sinaimg.cn/bmiddle/00617y0xgw1eqzb8ila7pj30go0avq4c.jpg</weibo_image>
    <weibo_count like_count="0" forward_count="0" comment_count="0"/>
    <weibo_date>10分钟前 </weibo_date>
    <weibo_from>来自微博 weibo.com</weibo_from>
  </weibo>
</root>
