<?xml version="1.0" encoding="UTF-8"?>

<root crawl_date="2015-04-09 14:51:45">
  <user_info user_id="5506179914" user_url="http://weibo.cn/u/5506179914?f=search_0">
    <weibo_count>5</weibo_count>
    <follow_count>0</follow_count>
    <fans_count>20</fans_count>
    <性别>男</性别>
    <生日>白羊座</生日>
    <head_image>http://tp3.sinaimg.cn/5506179914/180/5718639772/1</head_image>
    <昵称>么么Sn哒小雁</昵称>
    <地区>内蒙古</地区>
  </user_info>
  <weibo weibo_id="M_Cctk6fuxs">
    <weibo_sender>么么Sn哒小雁</weibo_sender>
    <weibo_content>:父亲在洗车,儿子拿起小石头在车门上划起来。父亲见此大怒,拿起扳手就打ī了下去后来儿子被送到医院,证实手指骨折。面对父亲,儿子轻声说道:“爸爸,手指会好的,不要担心了。” 父亲内心无比自责。一怒之下,冲回去要把自己的汽车给砸了,他看见儿子划的痕迹:爸爸,我爱你!</weibo_content>
    <weibo_image>http://ww2.sinaimg.cn/bmiddle/ac46cb8ftw1eongivuf0fj20dt07saa6.jpg</weibo_image>
    <weibo_count like_count="0" forward_count="0" comment_count="0"/>
    <weibo_date>15分钟前 </weibo_date>
    <weibo_from>来自微博 weibo.com</weibo_from>
  </weibo>
</root>
