<?xml version="1.0" encoding="UTF-8"?>

<root crawl_date="2015-04-09 14:48:17">
  <user_info user_id="1934362287" user_url="http://weibo.cn/u/1934362287?f=search_0">
    <weibo_count>10186</weibo_count>
    <follow_count>281</follow_count>
    <fans_count>929</fans_count>
    <性别>男</性别>
    <简介>喜欢赛车无忧无虑乐观的人</简介>
    <生日>01-01</生日>
    <tag>车世界,斯诺克,车迷,F1赛车</tag>
    <head_image>http://tp4.sinaimg.cn/1934362287/180/1295968661/1</head_image>
    <昵称>红爵男</昵称>
    <地区>山东 枣庄</地区>
  </user_info>
  <weibo weibo_id="M_Cctm8rxZw">
    <weibo_sender>红爵男</weibo_sender>
    <weibo_content>://超10款新车 哈弗品牌未来产品规划曝光 分享自@汽车之家 - http://t.cn/RAi1r89</weibo_content>
    <weibo_image>http://ww4.sinaimg.cn/bmiddle/734c06afjw1eqzba23aegj20b408cab1.jpg</weibo_image>
    <weibo_count like_count="0" forward_count="0" comment_count="0"/>
    <weibo_date>6分钟前 </weibo_date>
    <weibo_from>来自汽车之家Android版</weibo_from>
  </weibo>
</root>
