<?xml version="1.0" encoding="UTF-8"?>

<root crawl_date="2015-04-09 15:12:56">
  <user_info user_id="5505971566" user_url="http://weibo.cn/u/5505971566?f=search_0">
    <weibo_count>40</weibo_count>
    <follow_count>3</follow_count>
    <fans_count>10</fans_count>
    <性别>男</性别>
    <生日>双鱼座</生日>
    <head_image>http://tp3.sinaimg.cn/5505971566/180/5718473741/1</head_image>
    <昵称>翊G晨9</昵称>
    <地区>甘肃 金昌</地区>
  </user_info>
  <weibo weibo_id="M_Ccmn2e9FZ">
    <weibo_sender>翊G晨9</weibo_sender>
    <weibo_content>:【校车标准纷争 宇通客车回应质疑•】</weibo_content>
    <weibo_image>http://ww1.sinaimg.cn/bmiddle/abcf652ftw1eoo0wdkjxrj20c80p8myb.jpg</weibo_image>
    <weibo_count like_count="0" forward_count="0" comment_count="0"/>
    <weibo_date>04月08日 20:55 </weibo_date>
    <weibo_from>来自微博 weibo.com</weibo_from>
  </weibo>
</root>
