<?xml version="1.0" encoding="UTF-8"?>

<root crawl_date="2015-04-09 14:55:30">
  <user_info user_id="5505972928" user_url="http://weibo.cn/u/5505972928?f=search_0">
    <weibo_count>16</weibo_count>
    <follow_count>1</follow_count>
    <fans_count>4</fans_count>
    <性别>男</性别>
    <生日>双子座</生日>
    <head_image>http://tp1.sinaimg.cn/5505972928/180/5718476526/1</head_image>
    <昵称>鸡仔屎mu_</昵称>
    <地区>山东</地区>
  </user_info>
  <weibo weibo_id="M_CcsVhlnHy">
    <weibo_sender>鸡仔屎mu_</weibo_sender>
    <weibo_content>:【图解英菲尼迪JX】英菲尼迪刚刚推出的一款全新豪华七座SUV-JX,定位在FX与QX之间,满足商务用途的同时,兼顾家庭和社交场所的使♪用是JX最大的亮点之一。另外,英菲尼迪计划2014年全系车型将改名,所有轿车以“Q”命名,所有SUV车型以“QX”命名。</weibo_content>
    <weibo_count like_count="0" forward_count="0" comment_count="1"/>
    <weibo_date>今天 13:36 </weibo_date>
    <weibo_from>来自微博 weibo.com</weibo_from>
  </weibo>
</root>
