<?xml version="1.0" encoding="UTF-8"?>

<root crawl_date="2015-04-09 15:09:57">
  <user_info user_id="5513314571" user_url="http://weibo.cn/u/5513314571?f=search_0">
    <weibo_count>37</weibo_count>
    <follow_count>0</follow_count>
    <fans_count>16</fans_count>
    <性别>男</性别>
    <head_image>http://tp4.sinaimg.cn/5513314571/180/5721758777/1</head_image>
    <昵称>排魔盛俯</昵称>
    <地区>其他</地区>
  </user_info>
  <weibo weibo_id="M_CcoUjr1a4">
    <weibo_sender>排魔盛俯</weibo_sender>
    <weibo_content>:客车上,坐在首位的一位大婶突然呕吐起来,吐了几小袋,随手一捆就丢在车座的通道。到站,后面的人看到通道上装著的呕吐物嫌弃的不想越过,却又只有一个前门,这时,坐在大婶旁边的小女孩一声不吭的弯下腰捡起袋子冲下车。大婶下车,女孩对她说:“妈,丢脸死了。要不是这麽多人看著我才懒得捡……”</weibo_content>
    <weibo_image>http://ww2.sinaimg.cn/bmiddle/00617iYzjw1eqyrn0dtbrj30bs0cgwew.jpg</weibo_image>
    <weibo_count like_count="0" forward_count="0" comment_count="0"/>
    <weibo_date>今天 03:22 </weibo_date>
    <weibo_from>来自皮皮时光机</weibo_from>
  </weibo>
</root>
