<?xml version="1.0" encoding="UTF-8"?>

<root crawl_date="2015-04-09 15:17:35">
  <user_info user_id="5431872321" user_url="http://weibo.cn/u/5431872321?f=search_26">
    <weibo_count>7</weibo_count>
    <follow_count>37</follow_count>
    <fans_count>4</fans_count>
    <性别>男</性别>
    <生日>2005-02-02</生日>
    <tag>八卦杂谈</tag>
    <head_image>http://tp2.sinaimg.cn/5431872321/180/40073609780/1</head_image>
    <昵称>狐狸爱吃鱼-</昵称>
    <地区>浙江 杭州</地区>
  </user_info>
  <weibo weibo_id="M_Cckmouch0">
    <weibo_sender>狐狸爱吃鱼-</weibo_sender>
    <weibo_content>:在客车即将冲撞上来的一刻,瞬间推开了同学,简单本能的一个动作,确成为善和美的化身。让我们为这位善良勇敢的富阳学子何俊斌祈祷,早日康复,相信你一定会好起来! http://t.cn/RAJtNBt</weibo_content>
    <weibo_count like_count="0" forward_count="0" comment_count="0"/>
    <weibo_date>04月08日 15:48 </weibo_date>
    <weibo_from>来自微博 weibo.com</weibo_from>
  </weibo>
</root>
