<?xml version="1.0" encoding="UTF-8"?>

<root crawl_date="2015-04-09 15:14:38">
  <user_info user_id="5092490502" user_url="http://weibo.cn/u/5092490502?f=search_0">
    <weibo_count>33</weibo_count>
    <follow_count>20</follow_count>
    <fans_count>12</fans_count>
    <性别>女</性别>
    <简介>若有对翅膀:想飞的时候飞;想停的时候停!</简介>
    <生日>1981-07-22</生日>
    <head_image>http://tp3.sinaimg.cn/5092490502/180/5722659559/0</head_image>
    <昵称>飞鱼1981MEI</昵称>
    <地区>黑龙江 哈尔滨</地区>
  </user_info>
  <weibo weibo_id="M_Cclk2xMUQ">
    <weibo_sender>飞鱼1981MEI</weibo_sender>
    <weibo_content>:客车,第一次。二院,第一次。生命是个奇特的东西!像种子,像树苗,……</weibo_content>
    <weibo_image>http://ww4.sinaimg.cn/bmiddle/005yDzpAjw1eqybpoy7y5j30m80xcn0a.jpg</weibo_image>
    <weibo_count like_count="0" forward_count="0" comment_count="0"/>
    <weibo_date>04月08日 18:15 </weibo_date>
    <weibo_from>来自Android客户端</weibo_from>
  </weibo>
</root>
