<?xml version="1.0" encoding="UTF-8"?>

<root crawl_date="2015-04-09 14:53:55">
  <user_info user_id="5468212103" user_url="http://weibo.cn/u/5468212103?f=search_0">
    <weibo_count>8</weibo_count>
    <follow_count>120</follow_count>
    <fans_count>102</fans_count>
    <性别>男</性别>
    <head_image>http://tp4.sinaimg.cn/5468212103/180/5722033016/1</head_image>
    <昵称>画票镇</昵称>
    <地区>其他</地区>
  </user_info>
  <weibo weibo_id="M_CctcJsI5Y">
    <weibo_sender>画票镇</weibo_sender>
    <weibo_content>:【两头都能开的车】 俄罗斯发明家Shalom Bloch 改装了这辆两头都能开的小轿车,一头是自动档的,另外一头是手动挡的。这辆车最大的优点就是再也不用倒车,任何时候都是一往直前。</weibo_content>
    <weibo_count like_count="0" forward_count="0" comment_count="0"/>
    <weibo_date>35分钟前 </weibo_date>
    <weibo_from>来自微博 weibo.com</weibo_from>
  </weibo>
</root>
