<?xml version="1.0" encoding="UTF-8"?>

<root crawl_date="2015-03-30 20:45:36">
  <user_info user_id="5502184507" user_url="http://weibo.cn/u/5502184507?f=search_0">
    <weibo_count>19</weibo_count>
    <follow_count>7</follow_count>
    <fans_count>17</fans_count>
    <性别>男</性别>
    <生日>双鱼座</生日>
    <head_image>http://tp4.sinaimg.cn/5502184507/180/5717768927/1</head_image>
    <昵称>朱婷8c娜娜</昵称>
    <地区>宁夏 固原</地区>
  </user_info>
  <weibo weibo_id="M_CaZpkBnyW">
    <weibo_sender>朱婷8c娜娜</weibo_sender>
    <weibo_content>:【厦门首个汽车物流项目7月运营】5月17日讯,厦门汽车物流中心第一个专业配套项目——海西汽配城目前已经封顶,并将于7月份正式开业,目前已经销售逾96%。该项目占地面积约1万平方米,总建筑面积约2万平方米。项目建成↑后,将成为海西专业汽配、汽车用品市场的标杆之作,填补厦门没有专业</weibo_content>
    <weibo_count like_count="0" forward_count="0" comment_count="0"/>
    <weibo_date>9分钟前 </weibo_date>
    <weibo_from>来自微博 weibo.com</weibo_from>
  </weibo>
</root>
