<?xml version="1.0" encoding="UTF-8"?>

<root crawl_date="2015-03-30 20:47:38">
  <user_info user_id="1629996571" user_url="http://weibo.cn/sunny758?f=search_0">
    <weibo_count>1172</weibo_count>
    <follow_count>135</follow_count>
    <fans_count>368</fans_count>
    <性别>男</性别>
    <简介>真正有价值的人生,是我们自己是有价值的人并使别人的人生具有价值。看清人生百态,拒绝一切欺世盗名之门徒!</简介>
    <生日>天蝎座</生日>
    <达人>摄影 汽车 音乐</达人>
    <tag>汽车生活,西装控,音乐,Maksim,善良,中华养生文化,有心人</tag>
    <head_image>http://tp4.sinaimg.cn/1629996571/180/5718010771/1</head_image>
    <昵称>Alan_feng_秋城</昵称>
    <地区>广东 广州</地区>
  </user_info>
  <weibo weibo_id="M_CaZohieK5">
    <weibo_sender>Alan_feng_秋城</weibo_sender>
    <weibo_content>:家庭用车足矣~舒适且典雅大气-试驾江淮瑞风S3[超清版],mark一下。 (分享自 @土豆汽车) http://t.cn/RZkHh4N</weibo_content>
    <weibo_count like_count="0" forward_count="0" comment_count="0"/>
    <weibo_date>13分钟前 </weibo_date>
    <weibo_from>来自优酷土豆</weibo_from>
  </weibo>
</root>
