<?xml version="1.0" encoding="UTF-8"?>

<root crawl_date="2015-03-30 20:43:41">
  <user_info user_id="5479557873" user_url="http://weibo.cn/u/5479557873?f=search_0">
    <weibo_count>113</weibo_count>
    <follow_count>26</follow_count>
    <fans_count>112</fans_count>
    <性别>男</性别>
    <生日>狮子座</生日>
    <head_image>http://tp2.sinaimg.cn/5479557873/180/5716494856/1</head_image>
    <昵称>记忆A-無用</昵称>
    <地区>海外 澳大利亚</地区>
  </user_info>
  <weibo weibo_id="M_CaZqXDqK7">
    <weibo_sender>记忆A-無用</weibo_sender>
    <weibo_content>:【非法营运车拉客严重 南宁六大车站遭围堵】5月30日,在南宁市各大汽车站和火车站等6大车站进行调查发现,车站周边乱象横生,不但三轮车和摩的多,来抢客的面包车甚至组成“车队”在车站周边大肆拉客,车站ï部分往南宁周边县市的旅客被“抢走”,扰乱了客运市场,也严重影响车站周边的交通。</weibo_content>
    <weibo_count like_count="0" forward_count="0" comment_count="0"/>
    <weibo_date>3分钟前 </weibo_date>
    <weibo_from>来自微博 weibo.com</weibo_from>
  </weibo>
</root>
