<?xml version="1.0" encoding="UTF-8"?>

<root crawl_date="2015-03-30 20:49:42">
  <user_info user_id="5312476170" user_url="http://weibo.cn/u/5312476170?f=search_0">
    <weibo_count>102</weibo_count>
    <follow_count>125</follow_count>
    <fans_count>69</fans_count>
    <性别>女</性别>
    <生日>巨蟹座</生日>
    <head_image>http://tp3.sinaimg.cn/5312476170/180/5716091584/0</head_image>
    <昵称>呆萌Ml鹿萌萌刚好以后</昵称>
    <地区>浙江 丽水</地区>
  </user_info>
  <weibo weibo_id="M_CaZnna1pL">
    <weibo_sender>呆萌Ml鹿萌萌刚好以后</weibo_sender>
    <weibo_content>:【武汉成立汽车流通协会】10月24日′讯,为增加汽车销售商的话语权,武汉汽车流通行业协会近日正式成立。新当选的常务副会长兼秘书长王斌表示,当前与汽车制造厂商相比,流通领域的销售商话语权太弱。</weibo_content>
    <weibo_image>http://ww4.sinaimg.cn/bmiddle/ab7bf8a3jw1eonwelzlkgj20cs0crweh.jpg</weibo_image>
    <weibo_count like_count="0" forward_count="0" comment_count="0"/>
    <weibo_date>18分钟前 </weibo_date>
    <weibo_from>来自微博 weibo.com</weibo_from>
  </weibo>
</root>
