<?xml version="1.0" encoding="UTF-8"?>

<root crawl_date="2015-03-30 20:45:41">
  <user_info user_id="5391520084" user_url="http://weibo.cn/u/5391520084?f=search_0">
    <weibo_count>64</weibo_count>
    <follow_count>26</follow_count>
    <fans_count>32</fans_count>
    <性别>男</性别>
    <head_image>http://tp1.sinaimg.cn/5391520084/180/5714319093/1</head_image>
    <昵称>罩周防剂</昵称>
    <地区>其他</地区>
  </user_info>
  <weibo weibo_id="M_CaZpbFOTP">
    <weibo_sender>罩周防剂</weibo_sender>
    <weibo_content>:【汽车改装】意大利国旗颜色条纹兰博基尼LP670-4SV,极速:342km/h;加速:0-100km/h3.2s;最大功率:670HP。</weibo_content>
    <weibo_count like_count="0" forward_count="0" comment_count="0"/>
    <weibo_date>9分钟前 </weibo_date>
    <weibo_from>来自微博 weibo.com</weibo_from>
  </weibo>
</root>
