<?xml version="1.0" encoding="UTF-8"?>

<root crawl_date="2015-04-09 18:51:31">
  <user_info user_id="5543490231" user_url="http://weibo.cn/u/5543490231?f=search_0">
    <weibo_count>9</weibo_count>
    <follow_count>110</follow_count>
    <fans_count>5</fans_count>
    <性别>女</性别>
    <head_image>http://tp4.sinaimg.cn/5543490231/180/5723425273/0</head_image>
    <昵称>书子的梳子伯新茗</昵称>
    <地区>浙江 台州</地区>
  </user_info>
  <weibo weibo_id="M_CcuFf8tua" search_key="汽车">
    <weibo_sender>书子的梳子伯新茗</weibo_sender>
    <weibo_content>:【网友晒10年来都未涨价的9样东西】1、公交车,能打折;2、公园,免费多了;3、报纸:1元一份,越来越厚;4、食品,袋装醋依然一元;5、电子产品,价格越来越便宜;6、电话费上网费;7、汽车,开进寻常百姓家;8、彩票,2元可中1000万;9、工资! 第8条可亮了!最后一条很悲催,有木有!!</weibo_content>
    <weibo_count like_count="0" forward_count="0" comment_count="0"/>
    <weibo_date>50分钟前 </weibo_date>
    <weibo_from>来自微博 weibo.com</weibo_from>
  </weibo>
</root>
