<?xml version="1.0" encoding="UTF-8"?>

<root crawl_date="2015-04-09 19:22:01">
  <user_info user_id="1696464944" user_url="http://weibo.cn/wisterasis?f=search_0">
    <weibo_count>8400</weibo_count>
    <follow_count>352</follow_count>
    <fans_count>763</fans_count>
    <性别>女</性别>
    <简介>说什么脂正浓、粉正香,如何两鬓又成霜</简介>
    <生日>01-01</生日>
    <达人>美食 旅游 摄影</达人>
    <tag>爱烘焙,好奇心,音乐,宅女,摄影,旅行,爱猫猫,八卦</tag>
    <head_image>http://tp1.sinaimg.cn/1696464944/180/1298043447/0</head_image>
    <昵称>陈熊熊</昵称>
    <地区>上海</地区>
  </user_info>
  <weibo weibo_id="M_CcrUAa911" search_key="越野车">
    <weibo_sender>陈熊熊</weibo_sender>
    <weibo_content>【江苏:乘客高速抢夺客车方向盘 逃逸横穿被撞死[蜡烛]】昨天下午,乘客彭某与妻子发生口角,要求正在高速上行驶的大客车停车,遭司机拒绝后抢夺方向盘,造成客车撞上隔离护栏。彭某下车企图逃离现场时,被一辆越野车撞倒致死。目前案件仍在调查中[话筒](平安江苏)</weibo_content>
    <weibo_forward forward_reason="转发理由:越野车车主跑什么跑啊,傻了真是//@苦逼理性动物: 不作不死  "> 转发了 沈阳晚报 的微博:</weibo_forward>
    <weibo_image>http://ww3.sinaimg.cn/bmiddle/4c582bffjw1eqz3ilsm2xj20a10qo41n.jpg</weibo_image>
    <weibo_count like_count="0" forward_count="0" comment_count="0"/>
    <weibo_date>今天 11:01 </weibo_date>
    <weibo_from>来自微博 weibo.com</weibo_from>
  </weibo>
</root>
