<?xml version="1.0" encoding="UTF-8"?>

<root crawl_date="2015-04-09 19:12:33">
  <user_info user_id="5483791274" user_url="http://weibo.cn/u/5483791274?f=search_0">
    <weibo_count>94</weibo_count>
    <follow_count>834</follow_count>
    <fans_count>90</fans_count>
    <性别>女</性别>
    <生日>水瓶座</生日>
    <head_image>http://tp3.sinaimg.cn/5483791274/180/5716952037/0</head_image>
    <昵称>暖暖晴空安然q</昵称>
    <地区>广西 北海</地区>
  </user_info>
  <weibo weibo_id="M_CctALkeEm" search_key="轿车">
    <weibo_sender>暖暖晴空安然q</weibo_sender>
    <weibo_content>:【保時捷目前正在计划建造一款阶位低于Panamera的房車】这款新型轿车暂时被称为Pajun,动力系统方面,目前也确定将会提供V6与V8引擎,V6引擎会采用缸內直喷与涡轮增压系统,最大输出可达550hˇp,至于V8引擎则会配置双涡轮增压系统,最大马力将达到600hp。</weibo_content>
    <weibo_image>http://ww4.sinaimg.cn/bmiddle/be54554cjw1eoni6grmw3j20h80gbdhd.jpg</weibo_image>
    <weibo_count like_count="0" forward_count="0" comment_count="0"/>
    <weibo_date>今天 15:18 </weibo_date>
    <weibo_from>来自微博 weibo.com</weibo_from>
  </weibo>
</root>
