<?xml version="1.0" encoding="UTF-8"?>

<root crawl_date="2015-04-09 19:23:24">
  <user_info user_id="5494467791" user_url="http://weibo.cn/u/5494467791?f=search_0">
    <weibo_count>140</weibo_count>
    <follow_count>619</follow_count>
    <fans_count>47</fans_count>
    <性别>女</性别>
    <生日>双鱼座</生日>
    <head_image>http://tp4.sinaimg.cn/5494467791/180/5717140207/0</head_image>
    <昵称>爱凯永恒陪tH凯余生</昵称>
    <地区>天津 宁河县</地区>
  </user_info>
  <weibo weibo_id="M_CcrzFfe9N" search_key="越野车">
    <weibo_sender>爱凯永恒陪tH凯余生</weibo_sender>
    <weibo_content>:越野车¡不单能跑, 还能飞,</weibo_content>
    <weibo_image>http://ww2.sinaimg.cn/bmiddle/b6d30fffjw1eonf08lg0zj20et0m8754.jpg</weibo_image>
    <weibo_count like_count="0" forward_count="0" comment_count="0"/>
    <weibo_date>今天 10:10 </weibo_date>
    <weibo_from>来自微博 weibo.com</weibo_from>
  </weibo>
</root>
