<?xml version="1.0" encoding="UTF-8"?>

<root crawl_date="2015-04-09 19:05:56">
  <user_info user_id="1712356403" user_url="http://weibo.cn/hitfm?f=search_0">
    <weibo_count>5656</weibo_count>
    <follow_count>86</follow_count>
    <fans_count>3021295</fans_count>
    <性别>男</性别>
    <简介>Hit FM,是中国国际广播电台旗下的国际流行音乐广播,在北京地区播出频率为88.7兆赫、上海(FM87.9)、广州(FM88.5)。</简介>
    <生日>2003-04-16</生日>
    <tag>独家首播,HMA,TOP20,DJ,HitFM,CRI,Radio</tag>
    <认证>中国国际广播电台Hit FM官方微博、声动中国最受欢迎电台</认证>
    <head_image>http://tp4.sinaimg.cn/1712356403/180/40069180826/1</head_image>
    <认证信息>中国国际广播电台Hit FM官方微博、声动中国最受欢迎电台</认证信息>
    <昵称>HitFM</昵称>
    <地区>北京 石景山区</地区>
  </user_info>
  <weibo weibo_id="M_CcuEqyaQD" search_key="轿车">
    <weibo_sender>HitFM</weibo_sender>
    <weibo_content>:#Hit FM直播车#Cadillac On Air!Hit FM史上最强直播车,风尚运动豪华轿车—凯迪拉克ATS-L长轴版,风范,与Hit FM同行,明早首发,且听最具现场感的Hit Morning Show,欢迎小伙伴们各种围观评论。@凯迪拉克</weibo_content>
    <weibo_image>http://ww2.sinaimg.cn/bmiddle/66107c33gw1eqzbakcujgj20k00gj0uo.jpg</weibo_image>
    <weibo_count like_count="5" forward_count="1" comment_count="4"/>
    <weibo_date>今天 18:00 </weibo_date>
    <weibo_from>来自微博 weibo.com</weibo_from>
  </weibo>
</root>
