<?xml version="1.0" encoding="UTF-8"?>

<root crawl_date="2015-04-09 19:09:13">
  <user_info user_id="2019495361" user_url="http://weibo.cn/u/2019495361?f=search_0">
    <weibo_count>4148</weibo_count>
    <follow_count>292</follow_count>
    <fans_count>552</fans_count>
    <性别>男</性别>
    <简介>http://www.epcancer.com</简介>
    <感情状况>单身</感情状况>
    <生日>01-01</生日>
    <tag>广播,妖精,留学生,无锡生活,相声,美食,石家庄生活,IT数码,美女,职场招聘</tag>
    <head_image>http://tp2.sinaimg.cn/2019495361/180/5597069205/1</head_image>
    <昵称>越王轩主吧</昵称>
    <地区>河北 石家庄</地区>
  </user_info>
  <weibo weibo_id="M_Ccu9CyFTu" search_key="轿车">
    <weibo_sender>越王轩主吧</weibo_sender>
    <weibo_content>:近日,在河南周口,一女子开着捷豹轿车,纠集众人殴打、撞倒保安,叫嚣“用钱把你砸死在这儿”,行凶后一名男子还驾车加速冲撞出去。伤者家属多次到公安局询问进展,却一直没得到答复,民警甚至直接锁门离开。</weibo_content>
    <weibo_count like_count="0" forward_count="0" comment_count="0"/>
    <weibo_date>今天 16:44 </weibo_date>
    <weibo_from>来自微博 weibo.com</weibo_from>
  </weibo>
</root>
