<?xml version="1.0" encoding="UTF-8"?>

<root crawl_date="2015-04-09 19:38:25">
  <user_info user_id="1211834657" user_url="http://weibo.cn/511345112?f=search_0">
    <weibo_count>16058</weibo_count>
    <follow_count>275</follow_count>
    <fans_count>401</fans_count>
    <性别>男</性别>
    <简介>年轻人,你年轻的时候要欢乐。趁年少的日子,你的心只管好好享受。尽管走你心要走的路,照你眼所见的去行。不过你该知道,上帝要因这一切审判你。</简介>
    <生日>1989-02-14</生日>
    <达人>体育 音乐 文学</达人>
    <tag>伪足球迷,Watch,MR,本溪人,美剧迷,宅男80后,影迷,真基督徒</tag>
    <head_image>http://tp2.sinaimg.cn/1211834657/180/5695837437/1</head_image>
    <昵称>迟宏凯</昵称>
    <地区>天津 南开区</地区>
  </user_info>
  <weibo weibo_id="M_CctK6rEjn" search_key="客车">
    <weibo_sender>迟宏凯</weibo_sender>
    <weibo_content>#遇车祸推开同学被撞#【[话筒]帮帮何俊斌!扩散!】杭州富阳男孩何俊斌直面车祸时,一把推开同学,自己却被车撞击,经36个小时手术依然昏迷。目前医疗费约2万/天,其单身母亲已无法承担费用开始四处借债。@新浪浙江 联合@富阳发布 发起微公益,一起帮帮他!俊斌挺住!捐款请戳→→http://t.cn/RAijWIG</weibo_content>
    <weibo_forward forward_reason="转发理由:大客车司机怎么就不赔偿么?!卖房子卖地也得赔啊!!//@新浪天津:4月3日晚,天津农学院门口,一辆大客车超车时冲向学生,杭州的何俊斌及时推开身边的同学,自己却被撞昏迷,仍未苏醒。独自抚养他长大的母亲心如刀割,却无力承担大笔的治疗费用,谁能帮帮他们?[话筒]  "> 转发了 新浪浙江 的微博:</weibo_forward>
    <weibo_image>http://ww3.sinaimg.cn/bmiddle/7d000298jw1eqzb75vz4vj20c82s8163.jpg</weibo_image>
    <weibo_count like_count="0" forward_count="0" comment_count="0"/>
    <weibo_date>今天 15:41 </weibo_date>
    <weibo_from>来自迟宏凯的iPhone 6</weibo_from>
  </weibo>
</root>
