<?xml version="1.0" encoding="UTF-8"?>

<root crawl_date="2015-04-09 19:28:22">
  <user_info user_id="5503599092" user_url="http://weibo.cn/u/5503599092?f=search_0">
    <weibo_count>32</weibo_count>
    <follow_count>2</follow_count>
    <fans_count>16</fans_count>
    <性别>女</性别>
    <生日>巨蟹座</生日>
    <head_image>http://tp1.sinaimg.cn/5503599092/180/5718476439/0</head_image>
    <昵称>挥霍MW8emories</昵称>
    <地区>青海</地区>
  </user_info>
  <weibo weibo_id="M_Cck8ArRwI" search_key="越野车">
    <weibo_sender>挥霍MW8emories</weibo_sender>
    <weibo_content>:【进口奔驰GL350越野车被检出一重要安全缺陷】6月ˋ18日讯,记者从山东出入境检验检疫局了解到,山东黄岛检验检疫部门日前在对1辆进口梅赛德斯奔驰GL350越野车进行检验时发现,该车挡位存在安全缺陷,不符合我国机动车运行安全标准的相关要求,为此国家质检总局发出了相关风险警示通告</weibo_content>
    <weibo_count like_count="0" forward_count="0" comment_count="0"/>
    <weibo_date>04月08日 15:14 </weibo_date>
    <weibo_from>来自微博 weibo.com</weibo_from>
  </weibo>
</root>
