<?xml version="1.0" encoding="UTF-8"?>

<root crawl_date="2015-04-09 18:54:41">
  <user_info user_id="1735644267" user_url="http://weibo.cn/zihual?f=search_0">
    <weibo_count>7314</weibo_count>
    <follow_count>1344</follow_count>
    <fans_count>1444</fans_count>
    <性别>男</性别>
    <简介>曾经的,现在的,未来的梁梓华,S60L与我共同见证!</简介>
    <生日>巨蟹座</生日>
    <达人>汽车 音乐 财经</达人>
    <tag>坏人,音乐,VOLVO,S60,梁静茹,低调,听歌,汽车</tag>
    <认证>&amp;nbsp;&amp;nbsp;中山中裕丰田汽车销售服务有限公司金三分公司 市场专员</认证>
    <head_image>http://tp4.sinaimg.cn/1735644267/180/40080883587/1</head_image>
    <认证信息>&amp;nbsp;&amp;nbsp;中山中裕丰田汽车销售服务有限公司金三分公司 市场专员</认证信息>
    <昵称>Zi华S60L</昵称>
    <地区>广东 中山</地区>
  </user_info>
  <weibo weibo_id="M_CcuUEc99l" search_key="轿车">
    <weibo_sender>Zi华S60L</weibo_sender>
    <weibo_content>如果吉利果断放弃SUV,专注轿车,尤其是A级车。</weibo_content>
    <weibo_forward forward_reason="转发理由:我觉得没必要放弃一个领悟的车型,倒是可以精简一下各级别车型,把有市场潜力的车型保留,停产那些打酱油的,合理优化资源,集中力量做好做强就更适合了,对于长城这类偏科生,估计放弃轿车,也是无奈之举,其实保留凌奥,C30,C50还是不错的,特别是C30,贸然停产,给老车主多大的打击啊!  "> 转发了 周丽君12 的微博:</weibo_forward>
    <weibo_count like_count="0" forward_count="1" comment_count="0"/>
    <weibo_date>15分钟前 </weibo_date>
    <weibo_from>来自iPhone客户端</weibo_from>
  </weibo>
</root>
