<?xml version="1.0" encoding="UTF-8"?>

<root crawl_date="2015-04-09 19:11:48">
  <user_info user_id="5505876937" user_url="http://weibo.cn/u/5505876937?f=search_0">
    <weibo_count>20</weibo_count>
    <follow_count>2</follow_count>
    <fans_count>20</fans_count>
    <性别>女</性别>
    <生日>天秤座</生日>
    <head_image>http://tp2.sinaimg.cn/5505876937/180/5718478353/0</head_image>
    <昵称>梦rO在月荷</昵称>
    <地区>台湾 其他</地区>
  </user_info>
  <weibo weibo_id="M_CctKij6ai" search_key="轿车">
    <weibo_sender>梦rO在月荷</weibo_sender>
    <weibo_content>:【GL8强劲对手出现 东风本田艾力绅静态评测】真正的MPV是集轿车、商务车和旅行车功能于一身的多功能车型,可满足消费者多样化的需求。ELYSION艾力绅是一款完美体现新世代精英人士品位和风采的Stylish MPV,不仅强调大气外观和质感ξ内饰,还打造出凌驾于现有MPV之上的“</weibo_content>
    <weibo_image>http://ww4.sinaimg.cn/bmiddle/ad2e2871tw1eoo05f4jr7j20e609fjrs.jpg</weibo_image>
    <weibo_count like_count="0" forward_count="0" comment_count="0"/>
    <weibo_date>今天 15:41 </weibo_date>
    <weibo_from>来自微博 weibo.com</weibo_from>
  </weibo>
</root>
