<?xml version="1.0" encoding="UTF-8"?>

<root crawl_date="2015-04-09 19:08:20">
  <user_info user_id="2807074393" user_url="http://weibo.cn/u/2807074393?f=search_0">
    <weibo_count>106</weibo_count>
    <follow_count>521</follow_count>
    <fans_count>202</fans_count>
    <性别>男</性别>
    <head_image>http://tp2.sinaimg.cn/2807074393/180/5634436848/1</head_image>
    <昵称>M2明艺星星</昵称>
    <地区>其他</地区>
  </user_info>
  <weibo weibo_id="M_CcuiwelUy" search_key="轿车">
    <weibo_sender>M2明艺星星</weibo_sender>
    <weibo_content>:【轿车撞断电线杆司机遇难 福州连江消防救援】1月2º0日6时55分,福州市连江县城关往坑园镇方向路段,一辆小轿车突然失控撞向路边的电线杆,导致驾驶员当场身亡。据目击者透露,车辆当时几乎没有减速就失控撞上电线杆。目前,事故具体原因交警部门正在进一步调查当中。</weibo_content>
    <weibo_image>http://ww3.sinaimg.cn/bmiddle/a6cdd5d3tw1eonm8b1brrj20b40fqdge.jpg</weibo_image>
    <weibo_count like_count="0" forward_count="0" comment_count="0"/>
    <weibo_date>今天 17:06 </weibo_date>
    <weibo_from>来自微博 weibo.com</weibo_from>
  </weibo>
</root>
