<?xml version="1.0" encoding="UTF-8"?>

<root crawl_date="2015-04-09 18:49:16">
  <user_info user_id="3731419551" user_url="http://weibo.cn/fysbs?f=search_0">
    <weibo_count>99</weibo_count>
    <follow_count>90</follow_count>
    <fans_count>578</fans_count>
    <性别>男</性别>
    <简介>凤阳大小事,事事关心,欢迎私信或者@</简介>
    <生日>1989-09-28</生日>
    <tag>生活大爆炸,潮,名人明星,微博奇葩,搞笑幽默,滁州生活</tag>
    <认证>微博本地资讯博主(凤阳)http://t.cn/Rz7EQgx</认证>
    <head_image>http://tp4.sinaimg.cn/3731419551/180/40044297314/1</head_image>
    <认证信息>微博本地资讯博主(凤阳)http://t.cn/Rz7EQgx</认证信息>
    <昵称>凤阳身边事</昵称>
    <地区>安徽 滁州</地区>
  </user_info>
  <weibo weibo_id="M_CcuHPAzml" search_key="汽车">
    <weibo_sender>凤阳身边事</weibo_sender>
    <weibo_content>:#凤阳身边事#【违章拍你没商量】府北街和文昌街新增违章抓拍点:文昌街电信营业厅门口,文昌街医院门口,文昌街小中都门口,文昌街汽车站入口,府北街与府西街交口,府北街0048旁边,府北街菜市,府北街工行门口。文昌街4月7号已经开始使用,府北街这两天就要开始使用,开车的要休息了[哈哈]@中国凤阳</weibo_content>
    <weibo_image>http://ww1.sinaimg.cn/bmiddle/de68f19fjw1eqzh8dogymj208m06x0t1.jpg</weibo_image>
    <weibo_count like_count="0" forward_count="0" comment_count="0"/>
    <weibo_date>41分钟前 </weibo_date>
    <weibo_from>来自红米手机</weibo_from>
  </weibo>
</root>
